{
	"animations": [
		{
			"loop": false,
			"offsets": [
				226,
				172
			],
			"anim": "idle",
			"fps": 12,
			"name": "ralsei idle",
			"indices": []
		},
		{
			"loop": false,
			"offsets": [
				240,
				179
			],
			"anim": "singLEFT",
			"fps": 12,
			"name": "ralsei left",
			"indices": []
		},
		{
			"loop": false,
			"offsets": [
				253,
				174
			],
			"anim": "singDOWN",
			"fps": 12,
			"name": "ralsei down",
			"indices": []
		},
		{
			"loop": false,
			"offsets": [
				231,
				176
			],
			"anim": "singUP",
			"fps": 12,
			"name": "ralsei up",
			"indices": []
		},
		{
			"loop": false,
			"offsets": [
				261,
				170
			],
			"anim": "singRIGHT",
			"fps": 12,
			"name": "ralsei right",
			"indices": []
		}
	],
	"no_antialiasing": false,
	"image": "characters/ralsei",
	"position": [
		50,
		0
	],
	"healthicon": "ralsei-kris",
	"flip_x": true,
	"healthbar_colors": [
		31,
		161,
		115
	],
	"camera_position": [
		110,
		-50
	],
	"sing_duration": 4,
	"scale": 0.9
}